zeit3101helpers/__init__.py
zeit3101helpers/main.py
zeit3101helpers-0.0.14.dist-info/LICENSE
zeit3101helpers-0.0.14.dist-info/METADATA
zeit3101helpers-0.0.14.dist-info/WHEEL
zeit3101helpers-0.0.14.dist-info/top_level.txt
zeit3101helpers-0.0.14.dist-info/RECORD
