Metadata-Version: 2.1
Name: zeit3101helpers
Version: 0.0.14
Summary: ZEIT3101 Helper functions
Home-page: https://github.com/System-Not-Found/ZEIT3101
Download-URL: https://github.com/System-Not-Found/ZEIT3101/archive/v_01.tar.gz
Author: Ryan Cartwright
Author-email: fryzee.cartwright@gmail.com
License: MIT
Classifier: Development Status :: 3 - Alpha
Classifier: Intended Audience :: Developers
Classifier: Topic :: Software Development :: Build Tools
Classifier: License :: OSI Approved :: MIT License
Classifier: Programming Language :: Python :: 3.7
Classifier: Programming Language :: Python :: 3
License-File: LICENSE
Requires-Dist: pika
Requires-Dist: stix2
